{
  "type": "minecraft:crafting_shaped",
  "category": "misc",
  "pattern": [
    "B",
    "A"
  ],
  "key": {
    "A": "minecraft:copper_ingot",
    "B": "#obs:heads"
  },
  "result": {
    "id": "minecraft:trial_key",
    "count": 1,
              "components": {
                "minecraft:max_stack_size": 1,
                "minecraft:enchantment_glint_override": true,
                "minecraft:item_name": {
                  "translate": "obs.item.trial_key.name",
                  "fallback": "Trial Caller's Key",
                  "italic": false
                },
                "minecraft:lore": [
                  {
                  "translate": "obs.item.trial_key.lore",
                  "fallback": "-Summons a Trial Challenge when dropped into the void.",
                  "color": "gray",
                  "italic": false
                }
                ],
                "minecraft:custom_data": {
					"summon_trial":"true"
				}
              }
  }
}
